getmyancestors/__init__.py
getmyancestors/__main__.py
getmyancestors/fstogedcom.png
getmyancestors/fstogedcom.py
getmyancestors/getmyancestors.py
getmyancestors/mergemyancestors.py
getmyancestors/classes/__init__.py
getmyancestors/classes/constants.py
getmyancestors/classes/gedcom.py
getmyancestors/classes/gui.py
getmyancestors/classes/session.py
getmyancestors/classes/translation.py
getmyancestors/classes/tree.py
getmyancestors-1.1.2.dist-info/LICENSE
getmyancestors-1.1.2.dist-info/METADATA
getmyancestors-1.1.2.dist-info/WHEEL
getmyancestors-1.1.2.dist-info/entry_points.txt
getmyancestors-1.1.2.dist-info/top_level.txt
getmyancestors-1.1.2.dist-info/RECORD
