Metadata-Version: 2.2
Name: getmyancestors
Version: 1.1.2
Summary: Retrieve GEDCOM data from FamilySearch Tree
License: GNU
Project-URL: HomePage, https://github.com/Linekio/getmyancestors
Keywords: getmyancestors,familysearch,fstogedcom,gedcom
Classifier: Environment :: Console
Classifier: License :: OSI Approved :: GNU General Public License (GPL)
Classifier: Operating System :: OS Independent
Classifier: Programming Language :: Python :: 3 :: Only
Requires-Python: >=3.7
License-File: LICENSE
Requires-Dist: babelfish==0.6.1
Requires-Dist: diskcache==5.6.3
Requires-Dist: requests==2.32.3
Requires-Dist: fake-useragent==2.0.3
